{"v":"4.8.0","meta":{"g":"LottieFiles AE 3.5.4","a":"","k":"","d":"","tc":""},"fr":24,"ip":0,"op":102,"w":444,"h":444,"nm":"Air","ddd":0,"assets":[],"layers":[{"ddd":0,"ind":1,"ty":4,"nm":"3face mouth Outlines","sr":1,"ks":{"o":{"a":1,"k":[{"i":{"x":[0.833],"y":[0.833]},"o":{"x":[0.167],"y":[0.167]},"t":69,"s":[0]},{"t":71,"s":[100]}],"ix":11},"r":{"a":0,"k":0,"ix":10},"p":{"a":0,"k":[222.228,121.742,0],"ix":2},"a":{"a":0,"k":[21.408,16.342,0],"ix":1},"s":{"a":0,"k":[100,100,100],"ix":6}},"ao":0,"shapes":[{"ty":"gr","it":[{"ind":0,"ty":"sh","ix":1,"ks":{"a":0,"k":{"i":[[0,0],[2.672,2.134],[-3.175,3.126],[-3.519,-2.629],[0.963,-5.423],[4.775,2.142]],"o":[[1.32,-2.745],[-2.768,-2.212],[2.951,-2.904],[4.528,3.378],[-3.652,2.67],[0,0]],"v":[[-3.576,8.324],[-5.089,1.252],[-6.375,-7.188],[3.616,-7.844],[8.587,5.499],[-3.576,8.331]],"c":true},"ix":2},"nm":"Path 1","mn":"ADBE Vector Shape - Group","hd":false},{"ty":"fl","c":{"a":0,"k":[0.952941236309,0.690196078431,0.827451040231,1],"ix":4},"o":{"a":0,"k":100,"ix":5},"r":1,"bm":0,"nm":"Fill 1","mn":"ADBE Vector Graphic - Fill","hd":false},{"ty":"tr","p":{"a":0,"k":[22.395,21.96],"ix":2},"a":{"a":0,"k":[0,0],"ix":1},"s":{"a":0,"k":[100,100],"ix":3},"r":{"a":0,"k":0,"ix":6},"o":{"a":0,"k":100,"ix":7},"sk":{"a":0,"k":0,"ix":4},"sa":{"a":0,"k":0,"ix":5},"nm":"Transform"}],"nm":"Group 1","np":4,"cix":2,"bm":0,"ix":1,"mn":"ADBE Vector Group","hd":false},{"ty":"gr","it":[{"ind":0,"ty":"sh","ix":1,"ks":{"a":0,"k":{"i":[[0,0],[-2.049,8.73],[-2.754,0.378],[-8.637,-3.795],[0.884,-5.715],[5.499,-1.162],[4.528,3.387],[2.96,-2.903],[-2.768,-2.212],[1.32,-2.745]],"o":[[-9.087,-1.165],[0.714,-3.049],[9.091,-1.269],[4.801,2.111],[-0.916,5.904],[0.972,-5.423],[-3.518,-2.629],[-3.175,3.126],[2.672,2.134],[0,0]],"v":[[-2.589,15.017],[-19.109,-8.251],[-13.396,-13.397],[13.494,-11.222],[20.274,0.387],[9.582,12.194],[4.611,-1.151],[-5.38,-0.495],[-4.094,7.946],[-2.581,15.017]],"c":true},"ix":2},"nm":"Path 1","mn":"ADBE Vector Shape - Group","hd":false},{"ty":"fl","c":{"a":0,"k":[0,0,0,1],"ix":4},"o":{"a":0,"k":100,"ix":5},"r":1,"bm":0,"nm":"Fill 1","mn":"ADBE Vector Graphic - Fill","hd":false},{"ty":"tr","p":{"a":0,"k":[21.408,15.267],"ix":2},"a":{"a":0,"k":[0,0],"ix":1},"s":{"a":0,"k":[100,100],"ix":3},"r":{"a":0,"k":0,"ix":6},"o":{"a":0,"k":100,"ix":7},"sk":{"a":0,"k":0,"ix":4},"sa":{"a":0,"k":0,"ix":5},"nm":"Transform"}],"nm":"Group 2","np":4,"cix":2,"bm":0,"ix":2,"mn":"ADBE Vector Group","hd":false}],"ip":0,"op":173,"st":-67,"bm":0},{"ddd":0,"ind":2,"ty":4,"nm":"2face mouth Outlines","sr":1,"ks":{"o":{"a":1,"k":[{"i":{"x":[0.833],"y":[0.833]},"o":{"x":[0.167],"y":[0.167]},"t":-3,"s":[0]},{"i":{"x":[0.833],"y":[0.833]},"o":{"x":[0.167],"y":[0.167]},"t":-0.2,"s":[100]},{"i":{"x":[0.833],"y":[0.833]},"o":{"x":[0.167],"y":[0.167]},"t":29.4,"s":[100]},{"t":31.7998046875,"s":[0]}],"ix":11},"r":{"a":0,"k":0,"ix":10},"p":{"a":0,"k":[223.782,117.135,0],"ix":2},"a":{"a":0,"k":[24.997,14.612,0],"ix":1},"s":{"a":0,"k":[100,100,100],"ix":6}},"ao":0,"shapes":[{"ty":"gr","it":[{"ind":0,"ty":"sh","ix":1,"ks":{"a":0,"k":{"i":[[0,0],[-8.031,-1.206],[-0.389,1.693],[1.64,0.252],[8.848,-0.366],[-0.077,-1.655],[-1.663,0.068]],"o":[[8.283,-0.335],[1.533,0.228],[0.321,-1.411],[-8.756,-1.312],[-1.556,0.061],[0.068,1.556],[0,0]],"v":[[-12.89,2.398],[11.959,3.681],[15.62,1.605],[13.546,-2.056],[-12.89,-3.543],[-15.864,-0.569],[-12.89,2.406]],"c":true},"ix":2},"nm":"Path 1","mn":"ADBE Vector Shape - Group","hd":false},{"ty":"fl","c":{"a":0,"k":[0,0,0,1],"ix":4},"o":{"a":0,"k":100,"ix":5},"r":1,"bm":0,"nm":"Fill 1","mn":"ADBE Vector Graphic - Fill","hd":false},{"ty":"tr","p":{"a":0,"k":[23.902,15.486],"ix":2},"a":{"a":0,"k":[0,0],"ix":1},"s":{"a":0,"k":[100,100],"ix":3},"r":{"a":0,"k":0,"ix":6},"o":{"a":0,"k":100,"ix":7},"sk":{"a":0,"k":0,"ix":4},"sa":{"a":0,"k":0,"ix":5},"nm":"Transform"}],"nm":"Group 1","np":4,"cix":2,"bm":0,"ix":1,"mn":"ADBE Vector Group","hd":false},{"ty":"gr","it":[{"ind":0,"ty":"sh","ix":1,"ks":{"a":0,"k":{"i":[[0,0],[-0.374,-0.275],[-0.038,-0.03],[-0.122,-0.122],[-0.175,-0.198],[0.214,0.297],[0.008,0.008],[-0.107,-0.191],[-0.107,-0.183],[-0.122,-0.313],[-0.114,-0.419],[-0.046,-0.221],[0.061,0.671],[0,-0.442],[0.038,-0.45],[0.046,-0.244],[0.054,-0.221],[0.176,-0.428],[0.038,-0.076],[0.13,-0.213],[0.816,-0.877],[0.397,-0.358],[0.198,-0.168],[0.488,-0.366],[-0.877,-1.495],[-1.296,0.961],[0.008,5.758],[4.455,2.539],[0.755,-1.433],[-1.441,-0.823]],"o":[[0.404,0.229],[-0.465,-0.336],[0.13,0.122],[0.191,0.183],[0.046,0.053],[-0.213,-0.298],[0.115,0.183],[0.107,0.19],[0.267,0.488],[0.152,0.404],[0.053,0.214],[0.015,0.092],[0.038,0.442],[0,0.442],[0.038,-0.442],[-0.038,0.229],[-0.107,0.45],[0.191,-0.466],[-0.114,0.222],[-0.633,1.061],[-0.366,0.389],[-0.19,0.176],[-0.427,0.381],[-1.289,0.954],[0.74,1.266],[4.455,-3.31],[-0.007,-5.125],[-1.35,-0.771],[-0.755,1.434],[0,0]],"v":[[-3.771,-8.001],[-2.597,-7.253],[-2.353,-7.04],[-1.964,-6.674],[-1.415,-6.094],[-1.148,-5.781],[-0.927,-5.438],[-0.591,-4.881],[-0.286,-4.309],[-0.217,-4.187],[0.187,-2.952],[0.34,-2.311],[0.393,-2.059],[0.469,-0.732],[0.401,0.61],[0.37,0.763],[0.225,1.434],[-0.187,2.754],[-0.309,2.959],[-0.675,3.615],[-2.406,5.896],[-3.543,7.017],[-4.13,7.528],[-4.481,7.81],[-5.549,11.883],[-1.476,12.951],[6.418,-0.732],[-0.759,-13.141],[-4.832,-12.074],[-3.764,-8.001]],"c":true},"ix":2},"nm":"Path 1","mn":"ADBE Vector Shape - Group","hd":false},{"ty":"fl","c":{"a":0,"k":[0,0,0,1],"ix":4},"o":{"a":0,"k":100,"ix":5},"r":1,"bm":0,"nm":"Fill 1","mn":"ADBE Vector Graphic - Fill","hd":false},{"ty":"tr","p":{"a":0,"k":[6.676,14.162],"ix":2},"a":{"a":0,"k":[0,0],"ix":1},"s":{"a":0,"k":[100,100],"ix":3},"r":{"a":0,"k":0,"ix":6},"o":{"a":0,"k":100,"ix":7},"sk":{"a":0,"k":0,"ix":4},"sa":{"a":0,"k":0,"ix":5},"nm":"Transform"}],"nm":"Group 2","np":4,"cix":2,"bm":0,"ix":2,"mn":"ADBE Vector Group","hd":false},{"ty":"gr","it":[{"ind":0,"ty":"sh","ix":1,"ks":{"a":0,"k":{"i":[[0,0],[1.792,-4.699],[-1.64,-4.127],[-1.647,0.534],[0.617,1.549],[0.206,0.938],[0.046,0.244],[-0.046,-0.412],[0.015,0.48],[-0.031,0.473],[-0.016,0.198],[-0.053,0.214],[-0.32,0.869],[0.29,-0.633],[-0.084,0.184],[-0.229,0.381],[-0.297,0.397],[-0.053,0.061],[-0.175,0.184],[-0.358,0.313],[-0.167,0.137],[-0.511,0.351],[-1.03,0.504],[0.771,1.312],[1.45,-0.71]],"o":[[-4.508,2.197],[-1.594,4.179],[0.572,1.441],[1.396,-0.45],[-0.351,-0.892],[-0.053,-0.236],[-0.061,-0.328],[-0.054,-0.48],[-0.015,-0.481],[0.015,-0.199],[0.053,-0.671],[0.236,-0.892],[0.053,-0.145],[0.084,-0.183],[0.198,-0.396],[0.259,-0.42],[-0.389,0.534],[0.168,-0.191],[0.328,-0.343],[0.168,-0.145],[0.511,-0.435],[0.938,-0.656],[1.441,-0.702],[-0.862,-1.472],[0,0]],"v":[[3.295,-12.813],[-6.529,-2.249],[-6.262,10.923],[-2.601,12.997],[-0.526,9.335],[-1.381,6.598],[-1.526,5.874],[-1.548,5.82],[-1.663,4.378],[-1.64,2.945],[-1.594,2.35],[-1.579,2.197],[-0.885,-0.449],[-0.832,-0.632],[-0.58,-1.182],[0.061,-2.356],[0.892,-3.584],[1.052,-3.768],[1.563,-4.333],[2.593,-5.324],[3.096,-5.751],[3.348,-5.941],[6.285,-7.68],[7.352,-11.753],[3.279,-12.82]],"c":true},"ix":2},"nm":"Path 1","mn":"ADBE Vector Shape - Group","hd":false},{"ty":"fl","c":{"a":0,"k":[0,0,0,1],"ix":4},"o":{"a":0,"k":100,"ix":5},"r":1,"bm":0,"nm":"Fill 1","mn":"ADBE Vector Graphic - Fill","hd":false},{"ty":"tr","p":{"a":0,"k":[41.62,15.444],"ix":2},"a":{"a":0,"k":[0,0],"ix":1},"s":{"a":0,"k":[100,100],"ix":3},"r":{"a":0,"k":0,"ix":6},"o":{"a":0,"k":100,"ix":7},"sk":{"a":0,"k":0,"ix":4},"sa":{"a":0,"k":0,"ix":5},"nm":"Transform"}],"nm":"Group 3","np":4,"cix":2,"bm":0,"ix":3,"mn":"ADBE Vector Group","hd":false}],"ip":0,"op":173,"st":-67,"bm":0},{"ddd":0,"ind":3,"ty":4,"nm":"mouth Outlines","sr":1,"ks":{"o":{"a":1,"k":[{"i":{"x":[0.833],"y":[0.833]},"o":{"x":[0.167],"y":[0.167]},"t":-0.6,"s":[100]},{"i":{"x":[0.833],"y":[0.833]},"o":{"x":[0.167],"y":[0.167]},"t":-0.2,"s":[0]},{"i":{"x":[0.833],"y":[0.833]},"o":{"x":[0.167],"y":[0.167]},"t":29.4,"s":[0]},{"i":{"x":[0.833],"y":[0.833]},"o":{"x":[0.167],"y":[0.167]},"t":31.8,"s":[100]},{"i":{"x":[0.833],"y":[0.833]},"o":{"x":[0.167],"y":[0.167]},"t":69,"s":[100]},{"t":71,"s":[0]}],"ix":11},"r":{"a":0,"k":0,"ix":10},"p":{"a":0,"k":[218.061,117.513,0],"ix":2},"a":{"a":0,"k":[18.675,13.038,0],"ix":1},"s":{"a":0,"k":[100,100,100],"ix":6}},"ao":0,"shapes":[{"ty":"gr","it":[{"ind":0,"ty":"sh","ix":1,"ks":{"a":0,"k":{"i":[[0,0],[2.541,0.225],[2.685,-6.21],[1.394,-0.614],[1.066,1.393],[-1.229,1.209],[-0.943,2.132],[2.09,2.254],[-1.926,1.701],[-1.558,-1.292],[-0.062,-0.266],[-5.615,-0.04],[-2.377,-0.123],[0.185,-3.422],[2.562,0.103],[1.106,0]],"o":[[-1.968,-0.164],[-5.349,-0.492],[-0.635,1.455],[-1.619,0.718],[-1.148,-1.496],[1.558,-1.558],[1.23,-2.828],[-1.578,-1.681],[2.132,-1.885],[0.266,0.225],[2.029,7.747],[2.377,0],[2.419,0.123],[-0.184,3.197],[-0.512,-0.02],[0,0]],"v":[[10.822,4.714],[3.771,4.12],[-9.488,9.469],[-13.178,12.07],[-17.277,11.005],[-16.682,6.906],[-12.255,2.029],[-13.628,-5.492],[-13.833,-10.904],[-8.546,-9.612],[-7.828,-8.915],[6.066,-2.44],[13.219,-2.276],[18.24,1.332],[12.952,4.693],[10.822,4.693]],"c":true},"ix":2},"nm":"Path 1","mn":"ADBE Vector Shape - Group","hd":false},{"ty":"fl","c":{"a":0,"k":[0,0,0,1],"ix":4},"o":{"a":0,"k":100,"ix":5},"r":1,"bm":0,"nm":"Fill 1","mn":"ADBE Vector Graphic - Fill","hd":false},{"ty":"tr","p":{"a":0,"k":[18.674,13.038],"ix":2},"a":{"a":0,"k":[0,0],"ix":1},"s":{"a":0,"k":[100,100],"ix":3},"r":{"a":0,"k":0,"ix":6},"o":{"a":0,"k":100,"ix":7},"sk":{"a":0,"k":0,"ix":4},"sa":{"a":0,"k":0,"ix":5},"nm":"Transform"}],"nm":"Group 1","np":4,"cix":2,"bm":0,"ix":1,"mn":"ADBE Vector Group","hd":false}],"ip":0,"op":80.6,"st":-67,"bm":0},{"ddd":0,"ind":4,"ty":4,"nm":"eye R Outlines","sr":1,"ks":{"o":{"a":1,"k":[{"i":{"x":[0.833],"y":[0.833]},"o":{"x":[0.167],"y":[0.167]},"t":11.4,"s":[100]},{"i":{"x":[0.833],"y":[0.833]},"o":{"x":[0.167],"y":[0.167]},"t":11.8,"s":[0]},{"i":{"x":[0.833],"y":[0.833]},"o":{"x":[0.167],"y":[0.167]},"t":14.6,"s":[0]},{"i":{"x":[0.833],"y":[0.833]},"o":{"x":[0.167],"y":[0.167]},"t":15,"s":[100]},{"i":{"x":[0.833],"y":[0.833]},"o":{"x":[0.167],"y":[0.167]},"t":63.399,"s":[100]},{"i":{"x":[0.833],"y":[0.833]},"o":{"x":[0.167],"y":[0.167]},"t":63.8,"s":[0]},{"i":{"x":[0.833],"y":[0.833]},"o":{"x":[0.167],"y":[0.167]},"t":66.6,"s":[0]},{"i":{"x":[0.833],"y":[0.833]},"o":{"x":[0.167],"y":[0.167]},"t":67,"s":[100]},{"i":{"x":[0.833],"y":[0.833]},"o":{"x":[0.167],"y":[0.167]},"t":83.8,"s":[100]},{"i":{"x":[0.833],"y":[0.833]},"o":{"x":[0.167],"y":[0.167]},"t":84.2,"s":[0]},{"i":{"x":[0.833],"y":[0.833]},"o":{"x":[0.167],"y":[0.167]},"t":87,"s":[0]},{"t":87.3994140625,"s":[100]}],"ix":11},"r":{"a":0,"k":0,"ix":10},"p":{"a":0,"k":[244.386,98.894,0],"ix":2},"a":{"a":0,"k":[4.38,4.4,0],"ix":1},"s":{"a":0,"k":[100,100,100],"ix":6}},"ao":0,"shapes":[{"ty":"gr","it":[{"ind":0,"ty":"sh","ix":1,"ks":{"a":0,"k":{"i":[[0,0],[2.725,0],[0,2.48],[-2.726,-0.021],[-0.532,-1.804]],"o":[[-0.369,2.992],[-2.788,0],[0,-2.541],[2.787,0],[0,0]],"v":[[4.13,-0.399],[-0.154,4.15],[-4.13,-0.051],[-0.031,-4.129],[4.109,-0.399]],"c":true},"ix":2},"nm":"Path 1","mn":"ADBE Vector Shape - Group","hd":false},{"ty":"fl","c":{"a":0,"k":[0,0,0,1],"ix":4},"o":{"a":0,"k":100,"ix":5},"r":1,"bm":0,"nm":"Fill 1","mn":"ADBE Vector Graphic - Fill","hd":false},{"ty":"tr","p":{"a":0,"k":[4.38,4.4],"ix":2},"a":{"a":0,"k":[0,0],"ix":1},"s":{"a":0,"k":[100,100],"ix":3},"r":{"a":0,"k":0,"ix":6},"o":{"a":0,"k":100,"ix":7},"sk":{"a":0,"k":0,"ix":4},"sa":{"a":0,"k":0,"ix":5},"nm":"Transform"}],"nm":"Group 1","np":4,"cix":2,"bm":0,"ix":1,"mn":"ADBE Vector Group","hd":false}],"ip":0,"op":147.4,"st":-67,"bm":0},{"ddd":0,"ind":5,"ty":4,"nm":"eye L Outlines","sr":1,"ks":{"o":{"a":1,"k":[{"i":{"x":[0.833],"y":[0.833]},"o":{"x":[0.167],"y":[0.167]},"t":11.4,"s":[100]},{"i":{"x":[0.833],"y":[0.833]},"o":{"x":[0.167],"y":[0.167]},"t":11.8,"s":[0]},{"i":{"x":[0.833],"y":[0.833]},"o":{"x":[0.167],"y":[0.167]},"t":14.6,"s":[0]},{"i":{"x":[0.833],"y":[0.833]},"o":{"x":[0.167],"y":[0.167]},"t":15,"s":[100]},{"i":{"x":[0.833],"y":[0.833]},"o":{"x":[0.167],"y":[0.167]},"t":63.399,"s":[100]},{"i":{"x":[0.833],"y":[0.833]},"o":{"x":[0.167],"y":[0.167]},"t":63.8,"s":[0]},{"i":{"x":[0.833],"y":[0.833]},"o":{"x":[0.167],"y":[0.167]},"t":66.6,"s":[0]},{"i":{"x":[0.833],"y":[0.833]},"o":{"x":[0.167],"y":[0.167]},"t":67,"s":[100]},{"i":{"x":[0.833],"y":[0.833]},"o":{"x":[0.167],"y":[0.167]},"t":83.8,"s":[100]},{"i":{"x":[0.833],"y":[0.833]},"o":{"x":[0.167],"y":[0.167]},"t":84.2,"s":[0]},{"i":{"x":[0.833],"y":[0.833]},"o":{"x":[0.167],"y":[0.167]},"t":87,"s":[0]},{"t":87.3994140625,"s":[100]}],"ix":11},"r":{"a":0,"k":0,"ix":10},"p":{"a":0,"k":[202.527,93.627,0],"ix":2},"a":{"a":0,"k":[5.005,4.83,0],"ix":1},"s":{"a":0,"k":[100,100,100],"ix":6}},"ao":0,"shapes":[{"ty":"gr","it":[{"ind":0,"ty":"sh","ix":1,"ks":{"a":0,"k":{"i":[[2.582,-0.246],[0.205,2.972],[-2.521,0],[-0.287,-2.91]],"o":[[-2.89,-0.205],[-0.144,-2.562],[3.053,0],[0.246,2.521]],"v":[[0.246,4.581],[-4.611,-0.133],[-0.84,-4.581],[4.509,0.482]],"c":true},"ix":2},"nm":"Path 1","mn":"ADBE Vector Shape - Group","hd":false},{"ty":"fl","c":{"a":0,"k":[0,0,0,1],"ix":4},"o":{"a":0,"k":100,"ix":5},"r":1,"bm":0,"nm":"Fill 1","mn":"ADBE Vector Graphic - Fill","hd":false},{"ty":"tr","p":{"a":0,"k":[5.005,4.831],"ix":2},"a":{"a":0,"k":[0,0],"ix":1},"s":{"a":0,"k":[100,100],"ix":3},"r":{"a":0,"k":0,"ix":6},"o":{"a":0,"k":100,"ix":7},"sk":{"a":0,"k":0,"ix":4},"sa":{"a":0,"k":0,"ix":5},"nm":"Transform"}],"nm":"Group 1","np":4,"cix":2,"bm":0,"ix":1,"mn":"ADBE Vector Group","hd":false}],"ip":0,"op":145.4,"st":-67,"bm":0},{"ddd":0,"ind":6,"ty":4,"nm":"left hand Outlines","sr":1,"ks":{"o":{"a":0,"k":100,"ix":11},"r":{"a":1,"k":[{"i":{"x":[0.833],"y":[0.833]},"o":{"x":[0.167],"y":[0.167]},"t":-14.2,"s":[0]},{"i":{"x":[0.833],"y":[0.833]},"o":{"x":[0.167],"y":[0.167]},"t":-3,"s":[7]},{"i":{"x":[0.833],"y":[0.833]},"o":{"x":[0.167],"y":[0.167]},"t":23,"s":[7]},{"t":73.3994140625,"s":[-13]}],"ix":10},"p":{"a":0,"k":[223.267,359.144,0],"ix":2},"a":{"a":0,"k":[138.104,211.753,0],"ix":1},"s":{"a":0,"k":[100,100,100],"ix":6}},"ao":0,"shapes":[{"ty":"gr","it":[{"ind":0,"ty":"sh","ix":1,"ks":{"a":0,"k":{"i":[[0,0],[0.134,0.134],[0.35,0.39],[0.257,0.297],[0.205,0.267],[0.318,0.432],[0.134,0.205],[0.329,0.514],[0.113,0.185],[0.298,0.544],[0.103,0.195],[0.267,0.554],[0.093,0.205],[0.226,0.586],[0.061,0.165],[0.216,0.668],[0.01,0.061],[-3.194,8.441],[3.029,5.463],[0,0],[6.347,1.715],[-21.535,21.648],[-7.364,1.653],[8.966,-29.196],[-3.46,-6.264],[0,0],[-5.289,-1.839],[-5.453,-5.576],[-0.133,-0.143],[-0.349,-0.4],[-0.257,-0.308],[-0.215,-0.278],[-0.308,-0.421],[-0.154,-0.216],[-0.309,-0.493],[-0.123,-0.206],[-0.288,-0.524],[-0.113,-0.216],[-0.247,-0.534],[-0.102,-0.216],[-0.216,-0.565],[-0.061,-0.185],[-0.205,-0.657],[-0.03,-0.082],[3.224,-8.441],[-3.009,-5.453],[0,0],[-6.326,-1.694],[21.484,-21.699],[7.364,-1.674],[-8.893,29.206],[3.471,6.244],[0,0],[5.33,1.859],[5.433,5.566]],"o":[[-0.133,-0.133],[-0.359,-0.38],[-0.267,-0.298],[-0.216,-0.257],[-0.329,-0.421],[-0.144,-0.195],[-0.349,-0.493],[-0.113,-0.174],[-0.329,-0.534],[-0.103,-0.196],[-0.288,-0.544],[-0.092,-0.195],[-0.257,-0.575],[-0.062,-0.164],[-0.247,-0.657],[-0.02,-0.061],[-2.629,-8.319],[1.263,-5.587],[0,0],[-3.461,-6.038],[-29.464,-7.99],[5.33,-5.351],[29.792,-6.675],[-1.971,6.408],[0,0],[3.03,5.217],[7.918,1.581],[0.134,0.144],[0.36,0.38],[0.267,0.298],[0.226,0.277],[0.319,0.41],[0.154,0.216],[0.329,0.482],[0.133,0.205],[0.309,0.513],[0.113,0.216],[0.277,0.524],[0.102,0.216],[0.247,0.555],[0.072,0.185],[0.237,0.637],[0.031,0.082],[2.599,8.329],[-1.264,5.577],[0,0],[3.471,5.977],[29.494,7.918],[-5.32,5.371],[-29.782,6.747],[1.952,-6.408],[0,0],[-3.029,-5.289],[-7.887,-1.602],[0,0]],"v":[[-28.252,27.799],[-28.642,27.409],[-29.69,26.259],[-30.47,25.366],[-31.096,24.575],[-32.072,23.301],[-32.483,22.706],[-33.5,21.196],[-33.828,20.652],[-34.773,19.04],[-35.081,18.454],[-35.913,16.801],[-36.18,16.195],[-36.919,14.459],[-37.104,13.966],[-37.803,11.984],[-37.854,11.8],[-37.217,-14.11],[-39.353,-30.695],[-39.271,-30.737],[-54.388,-41.766],[-72.319,-108.096],[-52.878,-118.828],[-6.347,-68.282],[-4.899,-49.263],[-4.971,-49.222],[7.774,-39.034],[28.2,-27.882],[28.611,-27.461],[29.679,-26.29],[30.46,-25.386],[31.127,-24.554],[32.072,-23.312],[32.534,-22.654],[33.5,-21.206],[33.879,-20.59],[34.773,-19.05],[35.112,-18.403],[35.903,-16.811],[36.2,-16.154],[36.909,-14.47],[37.114,-13.915],[37.792,-11.974],[37.874,-11.718],[37.156,14.192],[39.251,30.747],[39.179,30.788],[54.275,41.704],[72.37,107.983],[52.95,118.756],[6.295,68.323],[4.806,49.314],[4.888,49.273],[-7.918,38.962],[-28.262,27.789]],"c":true},"ix":2},"nm":"Path 1","mn":"ADBE Vector Shape - Group","hd":false},{"ty":"fl","c":{"a":0,"k":[0.686274509804,0.686274509804,0.686274509804,1],"ix":4},"o":{"a":0,"k":100,"ix":5},"r":1,"bm":0,"nm":"Fill 1","mn":"ADBE Vector Graphic - Fill","hd":false},{"ty":"tr","p":{"a":0,"k":[94.104,125.753],"ix":2},"a":{"a":0,"k":[0,0],"ix":1},"s":{"a":0,"k":[100,100],"ix":3},"r":{"a":0,"k":0,"ix":6},"o":{"a":0,"k":100,"ix":7},"sk":{"a":0,"k":0,"ix":4},"sa":{"a":0,"k":0,"ix":5},"nm":"Transform"}],"nm":"Group 1","np":4,"cix":2,"bm":0,"ix":1,"mn":"ADBE Vector Group","hd":false}],"ip":0,"op":173,"st":-67,"bm":0},{"ddd":0,"ind":7,"ty":4,"nm":"right hand Outlines","sr":1,"ks":{"o":{"a":0,"k":100,"ix":11},"r":{"a":1,"k":[{"i":{"x":[0.833],"y":[0.833]},"o":{"x":[0.167],"y":[0.167]},"t":-18.6,"s":[0]},{"i":{"x":[0.833],"y":[0.833]},"o":{"x":[0.167],"y":[0.167]},"t":-7.4,"s":[-7]},{"i":{"x":[0.833],"y":[0.833]},"o":{"x":[0.167],"y":[0.167]},"t":23,"s":[-7]},{"t":73.3994140625,"s":[13]}],"ix":10},"p":{"a":0,"k":[223.586,361.154,0],"ix":2},"a":{"a":0,"k":[50.104,213.753,0],"ix":1},"s":{"a":0,"k":[100,100,100],"ix":6}},"ao":0,"shapes":[{"ty":"gr","it":[{"ind":0,"ty":"sh","ix":1,"ks":{"a":0,"k":{"i":[[0,0],[-0.133,0.134],[-0.349,0.39],[-0.256,0.297],[-0.205,0.267],[-0.319,0.432],[-0.133,0.205],[-0.329,0.514],[-0.113,0.185],[-0.297,0.544],[-0.103,0.195],[-0.267,0.554],[-0.092,0.205],[-0.226,0.586],[-0.062,0.165],[-0.216,0.668],[-0.01,0.061],[3.193,8.441],[-3.03,5.463],[0,0],[-6.346,1.715],[21.536,21.638],[7.363,1.654],[-8.965,-29.197],[3.461,-6.265],[0,0],[5.288,-1.838],[5.454,-5.577],[0.133,-0.144],[0.349,-0.4],[0.257,-0.308],[0.216,-0.277],[0.308,-0.422],[0.154,-0.216],[0.308,-0.493],[0.123,-0.205],[0.287,-0.523],[0.113,-0.215],[0.247,-0.534],[0.103,-0.215],[0.215,-0.565],[0.062,-0.185],[0.205,-0.657],[0.031,-0.082],[-3.224,-8.442],[3.009,-5.453],[0,0],[6.326,-1.695],[-21.484,-21.7],[-7.364,-1.674],[8.894,29.206],[-3.472,6.244],[0,0],[-5.33,1.858],[-5.433,5.566]],"o":[[0.134,-0.133],[0.36,-0.38],[0.267,-0.298],[0.216,-0.257],[0.329,-0.421],[0.143,-0.195],[0.349,-0.493],[0.113,-0.174],[0.328,-0.534],[0.103,-0.196],[0.287,-0.544],[0.093,-0.195],[0.257,-0.575],[0.061,-0.164],[0.246,-0.657],[0.021,-0.061],[2.629,-8.319],[-1.264,-5.587],[0,0],[3.46,-6.038],[29.474,-7.979],[-5.329,-5.351],[-29.792,-6.675],[1.972,6.408],[0,0],[-3.029,5.217],[-7.918,1.581],[-0.133,0.143],[-0.36,0.38],[-0.267,0.298],[-0.226,0.277],[-0.318,0.411],[-0.154,0.215],[-0.329,0.482],[-0.133,0.205],[-0.308,0.513],[-0.113,0.216],[-0.277,0.524],[-0.103,0.216],[-0.246,0.555],[-0.072,0.184],[-0.236,0.637],[-0.031,0.082],[-2.598,8.328],[1.263,5.576],[0,0],[-3.471,5.977],[-29.495,7.917],[5.319,5.371],[29.781,6.747],[-1.951,-6.408],[0,0],[3.03,-5.289],[7.887,-1.602],[0,0]],"v":[[28.241,27.789],[28.631,27.399],[29.679,26.249],[30.459,25.356],[31.086,24.565],[32.062,23.291],[32.472,22.696],[33.489,21.186],[33.818,20.642],[34.762,19.03],[35.071,18.444],[35.902,16.791],[36.169,16.185],[36.909,14.449],[37.094,13.956],[37.792,11.974],[37.843,11.79],[37.207,-14.12],[39.343,-30.705],[39.261,-30.747],[54.377,-41.776],[72.318,-108.096],[52.878,-118.828],[6.346,-68.281],[4.898,-49.262],[4.97,-49.221],[-7.774,-39.034],[-28.201,-27.881],[-28.611,-27.46],[-29.679,-26.29],[-30.46,-25.386],[-31.128,-24.554],[-32.072,-23.311],[-32.534,-22.654],[-33.5,-21.206],[-33.88,-20.59],[-34.773,-19.05],[-35.112,-18.403],[-35.903,-16.811],[-36.201,-16.154],[-36.909,-14.469],[-37.115,-13.915],[-37.792,-11.974],[-37.875,-11.717],[-37.156,14.193],[-39.251,30.747],[-39.179,30.788],[-54.275,41.705],[-72.37,107.984],[-52.95,118.756],[-6.296,68.323],[-4.806,49.314],[-4.889,49.273],[7.918,38.963],[28.262,27.789]],"c":true},"ix":2},"nm":"Path 1","mn":"ADBE Vector Shape - Group","hd":false},{"ty":"fl","c":{"a":0,"k":[0.686274509804,0.686274509804,0.686274509804,1],"ix":4},"o":{"a":0,"k":100,"ix":5},"r":1,"bm":0,"nm":"Fill 1","mn":"ADBE Vector Graphic - Fill","hd":false},{"ty":"tr","p":{"a":0,"k":[94.104,125.753],"ix":2},"a":{"a":0,"k":[0,0],"ix":1},"s":{"a":0,"k":[100,100],"ix":3},"r":{"a":0,"k":0,"ix":6},"o":{"a":0,"k":100,"ix":7},"sk":{"a":0,"k":0,"ix":4},"sa":{"a":0,"k":0,"ix":5},"nm":"Transform"}],"nm":"Group 1","np":4,"cix":2,"bm":0,"ix":1,"mn":"ADBE Vector Group","hd":false}],"ip":0,"op":173,"st":-67,"bm":0},{"ddd":0,"ind":8,"ty":4,"nm":"body Outlines","sr":1,"ks":{"o":{"a":0,"k":100,"ix":11},"r":{"a":0,"k":0,"ix":10},"p":{"a":0,"k":[225.267,360.643,0],"ix":2},"a":{"a":0,"k":[53.071,293.333,0],"ix":1},"s":{"a":0,"k":[100,100,100],"ix":6}},"ao":0,"shapes":[{"ty":"gr","it":[{"ind":0,"ty":"sh","ix":1,"ks":{"a":0,"k":{"i":[[0,0],[-0.041,0.185],[-0.113,0.504],[-0.072,0.39],[-0.051,0.328],[-0.062,0.534],[-0.021,0.236],[-0.031,0.606],[-0.01,0.215],[0.01,0.626],[0,0.216],[0.041,0.616],[0.011,0.215],[0.082,0.627],[0.031,0.174],[0.133,0.688],[0.01,0.062],[6.87,5.854],[-0.02,6.244],[0,0],[-4.724,4.58],[29.309,8.544],[7.25,-2.115],[-21.956,-21.227],[0,-7.147],[0,0],[3.738,-4.159],[2.084,-7.507],[0.051,-0.185],[0.113,-0.513],[0.071,-0.39],[0.061,-0.359],[0.061,-0.524],[0.02,-0.267],[0.031,-0.575],[0.01,-0.247],[0,-0.595],[-0.01,-0.247],[-0.041,-0.595],[-0.021,-0.236],[-0.082,-0.606],[-0.021,-0.195],[-0.123,-0.668],[-0.01,-0.093],[-6.901,-5.833],[0,-6.224],[0,0],[4.714,-4.539],[-29.3,-8.616],[-7.25,2.095],[21.895,21.289],[-0.021,7.147],[0,0],[-3.769,4.2],[-2.064,7.496]],"o":[[0.051,-0.175],[0.133,-0.503],[0.082,-0.39],[0.061,-0.329],[0.092,-0.534],[0.031,-0.236],[0.062,-0.606],[0.01,-0.215],[0.031,-0.627],[0,-0.216],[-0.011,-0.616],[-0.011,-0.216],[-0.051,-0.627],[-0.02,-0.174],[-0.103,-0.699],[-0.01,-0.061],[-1.715,-8.554],[-3.8,-4.282],[0,0],[0.113,-6.962],[21.946,-21.227],[-7.25,-2.115],[-29.32,8.544],[4.817,4.662],[0,0],[-0.134,6.039],[-6.162,5.206],[-0.052,0.185],[-0.134,0.513],[-0.082,0.39],[-0.062,0.35],[-0.082,0.514],[-0.031,0.267],[-0.062,0.575],[-0.01,0.247],[-0.021,0.595],[0,0.247],[0.01,0.596],[0.021,0.237],[0.051,0.606],[0.031,0.195],[0.103,0.678],[0.02,0.092],[1.746,8.544],[3.8,4.272],[0,0],[-0.155,6.911],[-21.998,21.176],[7.25,2.136],[29.341,-8.472],[-4.806,-4.672],[0,0],[0.093,-6.101],[6.131,-5.217],[0,0]],"v":[[38.178,10.711],[38.322,10.177],[38.681,8.667],[38.928,7.507],[39.092,6.511],[39.327,4.919],[39.4,4.2],[39.554,2.382],[39.585,1.746],[39.626,-0.123],[39.616,-0.781],[39.544,-2.629],[39.492,-3.286],[39.297,-5.166],[39.215,-5.689],[38.866,-7.764],[38.825,-7.949],[25.752,-30.326],[19.61,-45.874],[19.518,-45.874],[27.426,-62.839],[11.097,-129.57],[-11.107,-129.57],[-27.436,-62.839],[-19.518,-45.494],[-19.424,-45.494],[-25.659,-30.418],[-38.157,-10.793],[-38.311,-10.228],[-38.681,-8.688],[-38.927,-7.528],[-39.112,-6.47],[-39.338,-4.919],[-39.42,-4.118],[-39.564,-2.383],[-39.595,-1.653],[-39.636,0.133],[-39.626,0.873],[-39.554,2.649],[-39.492,3.368],[-39.297,5.186],[-39.215,5.771],[-38.876,7.795],[-38.825,8.062],[-25.68,30.408],[-19.518,45.915],[-19.424,45.915],[-27.374,62.767],[-11.199,129.539],[11.004,129.59],[27.497,62.89],[19.62,45.525],[19.528,45.525],[25.762,30.305],[38.178,10.701]],"c":true},"ix":2},"nm":"Path 1","mn":"ADBE Vector Shape - Group","hd":false},{"ty":"fl","c":{"a":0,"k":[0.686274509804,0.686274509804,0.686274509804,1],"ix":4},"o":{"a":0,"k":100,"ix":5},"r":1,"bm":0,"nm":"Fill 1","mn":"ADBE Vector Graphic - Fill","hd":false},{"ty":"tr","p":{"a":0,"k":[49.642,131.935],"ix":2},"a":{"a":0,"k":[0,0],"ix":1},"s":{"a":0,"k":[100,100],"ix":3},"r":{"a":0,"k":0,"ix":6},"o":{"a":0,"k":100,"ix":7},"sk":{"a":0,"k":0,"ix":4},"sa":{"a":0,"k":0,"ix":5},"nm":"Transform"}],"nm":"Group 2","np":4,"cix":2,"bm":0,"ix":1,"mn":"ADBE Vector Group","hd":false}],"ip":0,"op":173,"st":-67,"bm":0}],"markers":[]}